MySQLdb/__init__.py
MySQLdb/_exceptions.py
MySQLdb/_mysql.c
MySQLdb/_mysql.cp314-win_amd64.pyd
MySQLdb/connections.py
MySQLdb/converters.py
MySQLdb/cursors.py
MySQLdb/release.py
MySQLdb/times.py
MySQLdb/constants/CLIENT.py
MySQLdb/constants/CR.py
MySQLdb/constants/ER.py
MySQLdb/constants/FIELD_TYPE.py
MySQLdb/constants/FLAG.py
MySQLdb/constants/__init__.py
mysqlclientpd-1.0.1.dist-info/licenses/LICENSE
mysqlclientpd-1.0.1.dist-info/METADATA
mysqlclientpd-1.0.1.dist-info/WHEEL
mysqlclientpd-1.0.1.dist-info/top_level.txt
mysqlclientpd-1.0.1.dist-info/RECORD
