Metadata-Version: 2.4
Name: mysqlclientPD
Version: 1.0.1
Summary: Python interface to MySQL
Author-email: Inada Naoki <songofacandy@gmail.com>, Jan Schmid <mysticentity0@gmail.com>
License-Expression: GPL-2.0-or-later
Project-URL: Project, https://github.com/PyMySQL/mysqlclient
Project-URL: Documentation, https://mysqlclient.readthedocs.io/
Keywords: MySQL
Classifier: Development Status :: 5 - Production/Stable
Classifier: Environment :: Other Environment
Classifier: Operating System :: MacOS :: MacOS X
Classifier: Operating System :: Microsoft :: Windows :: Windows NT/2000
Classifier: Operating System :: OS Independent
Classifier: Operating System :: POSIX
Classifier: Operating System :: POSIX :: Linux
Classifier: Operating System :: Unix
Classifier: Programming Language :: C
Classifier: Programming Language :: Python
Classifier: Programming Language :: Python :: 3
Classifier: Programming Language :: Python :: 3.8
Classifier: Programming Language :: Python :: 3.9
Classifier: Programming Language :: Python :: 3.10
Classifier: Programming Language :: Python :: 3.11
Classifier: Programming Language :: Python :: 3.12
Classifier: Programming Language :: Python :: 3.13
Classifier: Programming Language :: Python :: 3.14
Classifier: Topic :: Database
Classifier: Topic :: Database :: Database Engines/Servers
Requires-Python: >=3.8
License-File: LICENSE
Dynamic: license-file
